<?xml version="1.0" encoding="utf-8" ?>
<Defs>

<!--Pre-Electricity-->

  <ResearchProjectDef>
    <defName>RA_Dor_Blades</defName>
    <label>doratorian blades</label>
    <description>Craft ceremonial Doratorian blades.</description>
	<tab>RA_Doratorian</tab>
    <baseCost>200</baseCost>
    <techLevel>Medieval</techLevel>
    <prerequisites>
      <li>LongBlades</li>
    </prerequisites>
    <researchViewX>3.00</researchViewX>
    <researchViewY>5.60</researchViewY>
    <generalRules>
      <rulesStrings>
        <li>subject->doratorian blades</li>
        <li>subject_story->found themselves at the maw of a leiskwing, with only a blade to protect oneself</li>
        <li>subject_gerund->crafting ceremonial blades</li>
      </rulesStrings>
    </generalRules>
  </ResearchProjectDef>

<!--Electricity-->

  <ResearchProjectDef>
    <defName>RA_Dor_Firearms</defName>
    <label>doratorian firearms</label>
    <description>Craft basic Doratorian firearms.</description>
	<tab>RA_Doratorian</tab>
    <baseCost>250</baseCost>
    <techLevel>Industrial</techLevel>
    <prerequisites>
      <li>Gunsmithing</li>
    </prerequisites>
    <researchViewX>6.00</researchViewX>
    <researchViewY>3.40</researchViewY>
    <generalRules>
      <rulesStrings>
        <li>subject->doratorian firearms</li>
        <li>subject_story->crafted basic firearms to defend themselves and others</li>
        <li>subject_gerund->crafting basic firearms</li>
      </rulesStrings>
    </generalRules>
  </ResearchProjectDef>

<!--Microelectronics-->

<!--MultiAnalyzer-->

<!--Ship-->

</Defs>